CREDITS.rst
LICENSE
MANIFEST.in
Makefile.in
README-standalone.rst
README.rst
configure
configure.ac
setup.py
docs/_build/html/.buildinfo
docs/_build/html/__init__.py
docs/_build/html/configuration.html
docs/_build/html/contributing.html
docs/_build/html/finding-help.html
docs/_build/html/genindex.html
docs/_build/html/getting-started.html
docs/_build/html/index.html
docs/_build/html/installation.html
docs/_build/html/objects.inv
docs/_build/html/project-status.html
docs/_build/html/release-notes.html
docs/_build/html/reporting-bugs.html
docs/_build/html/requirements.html
docs/_build/html/search.html
docs/_build/html/searchindex.js
docs/_build/html/security-issues.html
docs/_build/html/source-code.html
docs/_build/html/troubleshooting.html
docs/_build/html/user-guides.html
docs/_build/html/_sources/configuration.rst.txt
docs/_build/html/_sources/contributing.rst.txt
docs/_build/html/_sources/finding-help.rst.txt
docs/_build/html/_sources/getting-started.rst.txt
docs/_build/html/_sources/index.rst.txt
docs/_build/html/_sources/installation.rst.txt
docs/_build/html/_sources/project-status.rst.txt
docs/_build/html/_sources/release-notes.rst.txt
docs/_build/html/_sources/reporting-bugs.rst.txt
docs/_build/html/_sources/requirements.rst.txt
docs/_build/html/_sources/security-issues.rst.txt
docs/_build/html/_sources/source-code.rst.txt
docs/_build/html/_sources/troubleshooting.rst.txt
docs/_build/html/_sources/user-guides.rst.txt
docs/_build/html/_sources/configuration-directives/WSGIAcceptMutex.rst.txt
docs/_build/html/_sources/configuration-directives/WSGIAccessScript.rst.txt
docs/_build/html/_sources/configuration-directives/WSGIApplicationGroup.rst.txt
docs/_build/html/_sources/configuration-directives/WSGIAuthGroupScript.rst.txt
docs/_build/html/_sources/configuration-directives/WSGIAuthUserScript.rst.txt
docs/_build/html/_sources/configuration-directives/WSGICallableObject.rst.txt
docs/_build/html/_sources/configuration-directives/WSGICaseSensitivity.rst.txt
mod_wsgi.egg-info/PKG-INFO
mod_wsgi.egg-info/SOURCES.txt
mod_wsgi.egg-info/dependency_links.txt
mod_wsgi.egg-info/entry_points.txt
mod_wsgi.egg-info/not-zip-safe
mod_wsgi.egg-info/top_level.txt
